src/__init__.py
src/read_config.py
tests/__init__.py
tests/test_config_reader.py
tests/test_config_reader_map_to_dataclass.py
sat_config_reader-0.0.1.dist-info/METADATA
sat_config_reader-0.0.1.dist-info/WHEEL
sat_config_reader-0.0.1.dist-info/top_level.txt
sat_config_reader-0.0.1.dist-info/RECORD
